my_nlp_framework/__init__.py
my_nlp_framework/core/__init__.py
my_nlp_framework/core/attention.py
my_nlp_framework/core/bpe_tokenizer.py
my_nlp_framework/core/embedding.py
my_nlp_framework/core/feed_forward.py
my_nlp_framework/core/lora.py
my_nlp_framework/core/model.py
my_nlp_framework/core/parser.py
my_nlp_framework/core/positional_encoding.py
my_nlp_framework/core/sequence_model.py
my_nlp_framework/core/tokenizer.py
my_nlp_framework/data/__init__.py
my_nlp_framework/data/loaders.py
my_nlp_framework/data/preprocessing.py
my_nlp_framework/evaluation/__init__.py
my_nlp_framework/evaluation/metrics.py
my_nlp_framework/models/__init__.py
my_nlp_framework/models/bert_model.py
my_nlp_framework/models/gpt_model.py
my_nlp_framework/models/hybrid_model.py
my_nlp_framework/models/transformer_model.py
my_nlp_framework/utils/__init__.py
my_nlp_framework/utils/helpers.py
my_nlp_framework/utils/optimization.py
zenith_nlp_framework-1.0.0.dist-info/METADATA
zenith_nlp_framework-1.0.0.dist-info/WHEEL
zenith_nlp_framework-1.0.0.dist-info/top_level.txt
zenith_nlp_framework-1.0.0.dist-info/RECORD
