Metadata-Version: 2.4
Name: zenith-nlp-framework
Version: 1.0.0
Summary: An advanced, from-scratch NLP framework for training and deploying modern transformer models.
Home-page: https://github.com/cattolatte/zenith-nlp-framework
Author: Satya Sai Nischal
Author-email: coderstale@gmail.com
Classifier: Programming Language :: Python :: 3.9
Classifier: License :: OSI Approved :: MIT License
Classifier: Operating System :: OS Independent
Classifier: Intended Audience :: Developers
Classifier: Intended Audience :: Science/Research
Classifier: Topic :: Scientific/Engineering :: Artificial Intelligence
Requires-Python: >=3.9
Dynamic: author
Dynamic: author-email
Dynamic: classifier
Dynamic: description
Dynamic: description-content-type
Dynamic: home-page
Dynamic: requires-python
Dynamic: summary
